setup.py
onesky/__init__.py
onesky/client.py
onesky/interactive.py
onesky_python.egg-info/PKG-INFO
onesky_python.egg-info/SOURCES.txt
onesky_python.egg-info/dependency_links.txt
onesky_python.egg-info/requires.txt
onesky_python.egg-info/top_level.txt