Metadata-Version: 1.0
Name: onesky-python
Version: 1.0
Summary: python wrapper for the OneSky REST API
Home-page: https://github.com/Jana-Mobile/onesky-python
Author: Dan OBrien
Author-email: danob@jana.com
License: LICENSE.txt
Platform: UNKNOWN
